karen/__init__.py
karen/actions.py
karen/classify.py
karen/combo.py
karen/evaluate.py
karen/getCombo.py
karen/logger.py
karen/output.py
karen/parameters.py
karen/state.py
karen-1.2.3.dist-info/licenses/LICENSE.txt
karen-1.2.3.dist-info/METADATA
karen-1.2.3.dist-info/WHEEL
karen-1.2.3.dist-info/top_level.txt
karen-1.2.3.dist-info/RECORD
