Metadata-Version: 2.4
Name: karen
Version: 1.2.3
Summary: Evaluates & categorises Spider-Man's combos in Marvel Rivals.
Home-page: https://github.com/EvilDuck14/Karen/
Author: EvilDuck
Author-email: theevilduck14@gmail.com
Project-URL: Discord, https://discord.gg/RpQf2zVAMP
Project-URL: Source, https://github.com/EvilDuck14/Karen/
License-File: LICENSE.txt
Dynamic: author
Dynamic: author-email
Dynamic: description
Dynamic: description-content-type
Dynamic: home-page
Dynamic: license-file
Dynamic: project-url
Dynamic: summary
